<?xml version="1.0" encoding="utf-8" ?>
<dwsync>
<file name="bk.jpg" server="C:/xampp/htdocs/topweb/" local="130261965834793945" remote="130261965830000000" Dst="0" />
<file name="menu_bk.jpg" server="C:/xampp/htdocs/topweb/" local="130261965757609530" remote="130261965750000000" Dst="0" />
<file name="table_bk.png" server="C:/xampp/htdocs/topweb/" local="130261965748178991" remote="130261965740000000" Dst="0" />
<file name="downmenu_bk.png" server="C:/xampp/htdocs/topweb/" local="130261965802452095" remote="130261965800000000" Dst="0" />
<file name="footer_bk.png" server="C:/xampp/htdocs/topweb/" local="130261965801032014" remote="130261965800000000" Dst="0" />
<file name="logo.png" server="C:/xampp/htdocs/topweb/" local="130261965793561586" remote="130261965790000000" Dst="0" />
<file name="treeMenu.gif" server="C:/xampp/htdocs/topweb/" local="130261965730367972" remote="130261965730000000" Dst="0" />
<file name="login_title.png" server="C:/xampp/htdocs/topweb/" local="130261965795961724" remote="130261965790000000" Dst="0" />
<file name="box.png" server="C:/xampp/htdocs/topweb/" local="130261965833523872" remote="130261965830000000" Dst="0" />
<file name="login_id.png" server="C:/xampp/htdocs/topweb/" local="130261965798311858" remote="130261965790000000" Dst="0" />
<file name="login_pw.png" server="C:/xampp/htdocs/topweb/" local="130261965797481811" remote="130261965790000000" Dst="0" />
<file name="login_code.png" server="C:/xampp/htdocs/topweb/" local="130261965800091960" remote="130261965800000000" Dst="0" />
<file name="btn_login.png" server="C:/xampp/htdocs/topweb/" local="130261965826363463" remote="130261965820000000" Dst="0" />
<file name="powerby.png" server="C:/xampp/htdocs/topweb/" local="130261965753029268" remote="130261965750000000" Dst="0" />
<file name="btn_add.png" server="C:/xampp/htdocs/topweb/" local="130261965831123735" remote="130261965830000000" Dst="0" />
<file name="btn_mod.png" server="C:/xampp/htdocs/topweb/" local="130261965823963325" remote="130261965820000000" Dst="0" />
<file name="btn_del.png" server="C:/xampp/htdocs/topweb/" local="130261965828723598" remote="130261965820000000" Dst="0" />
<file name="btn_line.png" server="C:/xampp/htdocs/topweb/" local="130261965827653536" remote="130261965820000000" Dst="0" />
<file name="btn_open.png" server="C:/xampp/htdocs/topweb/" local="130261965820563131" remote="130261965820000000" Dst="0" />
<file name="btn_close.png" server="C:/xampp/htdocs/topweb/" local="130261965830093676" remote="130261965830000000" Dst="0" />
<file name="loginbk.jpg" server="C:/xampp/htdocs/topweb/" local="130261965795081673" remote="130261965790000000" Dst="0" />
<file name="adminbk.jpg" server="C:/xampp/htdocs/topweb/" local="130261965841794345" remote="130261965840000000" Dst="0" />
<file name="btn_mail.png" server="C:/xampp/htdocs/topweb/" local="130261965825253399" remote="130261965820000000" Dst="0" />
<file name="btn_send.png" server="C:/xampp/htdocs/topweb/" local="130261965818122991" remote="130261965810000000" Dst="0" />
<file name="btn_nosend.png" server="C:/xampp/htdocs/topweb/" local="130261965821323174" remote="130261965820000000" Dst="0" />
<file name="btn_proc.png" server="C:/xampp/htdocs/topweb/" local="130261965819023043" remote="130261965810000000" Dst="0" />
<file name="btn_noproc.png" server="C:/xampp/htdocs/topweb/" local="130261965822963268" remote="130261965820000000" Dst="0" />
</dwsync>